README.rst
setup.py
bin/hrt
hrt/__init__.py
hrt/base.py
hrt/cli.py
hrt/input_handler.py
hrt/interface.py
hrt/plugin_manager.py
hrt/script.py
hrt/translator.py
hrt/url.py
hrt/util.py
hrt.egg-info/PKG-INFO
hrt.egg-info/SOURCES.txt
hrt.egg-info/dependency_links.txt
hrt.egg-info/top_level.txt
hrt/templates/__init__.py
hrt/templates/bash.py
hrt/templates/php.py
hrt/templates/python.py
hrt/templates/ruby.py