Metadata-Version: 1.0
Name: hrt
Version: 0.1.0
Summary: Translates raw HTTP requests to Python,Ruby,Php and Bash scripts
Home-page: https://github.com/owtf/http-request-translator/
Author: Ramana Subramanyam, Arun Sori, cjdupreez
Author-email: owasp_owtf_developers@lists.owasp.org
License: 3-clause BSD
Platform: UNKNOWN
